setup.py
GoogleMyMaps/GoogleMyMaps.py
GoogleMyMaps/__init__.py
GoogleMyMaps.egg-info/PKG-INFO
GoogleMyMaps.egg-info/SOURCES.txt
GoogleMyMaps.egg-info/dependency_links.txt
GoogleMyMaps.egg-info/requires.txt
GoogleMyMaps.egg-info/top_level.txt