Metadata-Version: 1.0
Name: GoogleMyMaps
Version: 1.1.0
Summary: Python parser for Google My Maps.
Home-page: https://github.com/nabehide/GoogleMyMaps
Author: UNKNOWN
Author-email: UNKNOWN
License: MIT
Platform: UNKNOWN
